odoo8_addon_pos_invoice_journal-8.0.1.0.0.99.dev10-py3.8-nspkg.pth
odoo_addons/pos_invoice_journal/README.rst
odoo_addons/pos_invoice_journal/__init__.py
odoo_addons/pos_invoice_journal/__openerp__.py
odoo_addons/pos_invoice_journal/i18n/de.po
odoo_addons/pos_invoice_journal/i18n/es.po
odoo_addons/pos_invoice_journal/i18n/fr.po
odoo_addons/pos_invoice_journal/i18n/it.po
odoo_addons/pos_invoice_journal/i18n/nl_NL.po
odoo_addons/pos_invoice_journal/i18n/pos_invoice_journal.pot
odoo_addons/pos_invoice_journal/i18n/sl.po
odoo_addons/pos_invoice_journal/i18n/zh_CN.po
odoo_addons/pos_invoice_journal/models/__init__.py
odoo_addons/pos_invoice_journal/models/pos_config.py
odoo_addons/pos_invoice_journal/models/pos_order.py
odoo_addons/pos_invoice_journal/static/description/icon.png
odoo_addons/pos_invoice_journal/static/description/icon.svg
odoo_addons/pos_invoice_journal/views/pos_config.xml
odoo8_addon_pos_invoice_journal-8.0.1.0.0.99.dev10.dist-info/METADATA
odoo8_addon_pos_invoice_journal-8.0.1.0.0.99.dev10.dist-info/WHEEL
odoo8_addon_pos_invoice_journal-8.0.1.0.0.99.dev10.dist-info/namespace_packages.txt
odoo8_addon_pos_invoice_journal-8.0.1.0.0.99.dev10.dist-info/top_level.txt
odoo8_addon_pos_invoice_journal-8.0.1.0.0.99.dev10.dist-info/RECORD
